pmccc/__init__.py
pmccc/pmccc.py
pmccc/types.py
pmccc/client/__init__.py
pmccc/client/assets.py
pmccc/client/launcher.py
pmccc/client/library.py
pmccc/client/minecraft.py
pmccc/client/namepath.py
pmccc/client/native.py
pmccc/client/player.py
pmccc/client/version.py
pmccc/install/__init__.py
pmccc/install/installer.py
pmccc/lib/__init__.py
pmccc/lib/config.py
pmccc/lib/info.py
pmccc/lib/java.py
pmccc/lib/mirror.py
pmccc/lib/network.py
pmccc/lib/path.py
pmccc/lib/rules.py
pmccc/lib/verify.py
pmccc/process/__init__.py
pmccc/process/log4j2.py
pmccc/process/log4j2.xml
pmccc/process/process.py
pmccc/server/__init__.py
pmccc/server/launcher.py
pmccc/server/rcon.py
pmccc/utils/__init__.py
pmccc/utils/daemon.py
pmccc/utils/export_script.py
pmccc/utils/portable.py
pmccc-0.4.3.dist-info/licenses/LICENSE
pmccc-0.4.3.dist-info/METADATA
pmccc-0.4.3.dist-info/WHEEL
pmccc-0.4.3.dist-info/top_level.txt
pmccc-0.4.3.dist-info/RECORD
