Metadata-Version: 2.4
Name: pmccc
Version: 0.4.3
Summary: A minecraft launcher library for python
Author-email: cueavyqwp <cueavy@outlook.com>
License-Expression: MIT
Project-URL: Homepage, https://github.com/cueavyqwp/pmccc
Project-URL: Bug, https://github.com/cueavyqwp/pmccc/issues
Project-URL: Source, https://github.com/cueavyqwp/pmccc.git
Project-URL: Documentation, https://github.com/cueavyqwp/pmccc/tree/main/docs
Keywords: minecraft,minecraft-launcher
Classifier: Programming Language :: Python :: 3
Classifier: Programming Language :: Python :: 3.10
Classifier: Topic :: Games/Entertainment
Requires-Python: >=3.10
License-File: LICENSE
Requires-Dist: charset_normalizer
Requires-Dist: requests
Requires-Dist: psutil
Dynamic: license-file
